MANIFEST.in
README.txt
setup.cfg
setup.py
mvob/__init__.py
mvob.InfoBlad.egg-info/PKG-INFO
mvob.InfoBlad.egg-info/SOURCES.txt
mvob.InfoBlad.egg-info/dependency_links.txt
mvob.InfoBlad.egg-info/entry_points.txt
mvob.InfoBlad.egg-info/namespace_packages.txt
mvob.InfoBlad.egg-info/not-zip-safe
mvob.InfoBlad.egg-info/paster_plugins.txt
mvob.InfoBlad.egg-info/requires.txt
mvob.InfoBlad.egg-info/top_level.txt
mvob/InfoBlad/README.txt
mvob/InfoBlad/__init__.py
mvob/InfoBlad/config.py
mvob/InfoBlad/configure.zcml
mvob/InfoBlad/browser/__init__.py
mvob/InfoBlad/browser/configure.zcml
mvob/InfoBlad/browser/infoblad_view.pt
mvob/InfoBlad/browser/infoblad_view.py
mvob/InfoBlad/browser/images/buttonNext.jpg
mvob/InfoBlad/browser/images/buttonPrev.jpg
mvob/InfoBlad/browser/images/light-alpha.png
mvob/InfoBlad/browser/javascripts/mediaAlbum.js
mvob/InfoBlad/browser/stylesheets/mediaAlbum.css
mvob/InfoBlad/content/__init__.py
mvob/InfoBlad/content/configure.zcml
mvob/InfoBlad/content/infoblad.py
mvob/InfoBlad/interfaces/__init__.py
mvob/InfoBlad/interfaces/infoblad.py
mvob/InfoBlad/portlets/__init__.py
mvob/InfoBlad/portlets/configure.zcml
mvob/InfoBlad/profiles/default/cssregistry.xml
mvob/InfoBlad/profiles/default/factorytool.xml
mvob/InfoBlad/profiles/default/jsregistry.xml
mvob/InfoBlad/profiles/default/metadata.xml
mvob/InfoBlad/profiles/default/portlets.xml
mvob/InfoBlad/profiles/default/rolemap.xml
mvob/InfoBlad/profiles/default/tinymce.xml
mvob/InfoBlad/profiles/default/types.xml
mvob/InfoBlad/profiles/default/types/InfoBlad.xml
mvob/InfoBlad/tests/__init__.py
mvob/InfoBlad/tests/base.py
mvob/InfoBlad/tests/test_doctest.py