Metadata-Version: 1.0
Name: mvob.InfoBlad
Version: 0.7
Summary: Type that is similar to Document but is folderish and has a view to display images in a photoalbum
Home-page: https://svn.v2.nl/plone/mvob.InfoBlad
Author: David Jonas
Author-email: david@v2.nl
License: GPL
Keywords: type archetype blad info
Platform: UNKNOWN
Classifier: Framework :: Plone
Classifier: Intended Audience :: Developers
Classifier: License :: OSI Approved :: GNU General Public License (GPL)
